gantt_csv/__init__.py
gantt_csv/gantt_csv.py
python_gantt_csv-0.4.0.dist-info/METADATA
python_gantt_csv-0.4.0.dist-info/WHEEL
python_gantt_csv-0.4.0.dist-info/top_level.txt
python_gantt_csv-0.4.0.dist-info/zip-safe
python_gantt_csv-0.4.0.dist-info/RECORD
