Metadata-Version: 2.1
Name: python-gantt-csv
Version: 0.4.0
Summary: python-gantt-csv manage gantt.Task arguments with csv format.
Home-page: https://gitlab.com/shotahorie/python-gantt-csv
Author: Shota Horie
Author-email: horie.shouta@gmail.com
License: gpl-3.0.txt
Keywords: gantt,graphics,scheduling,project management
Platform: Operating System :: OS Independent
Classifier: Development Status :: 4 - Beta
Classifier: Programming Language :: Python
Classifier: Environment :: Console
Classifier: Intended Audience :: Developers
Classifier: Intended Audience :: End Users/Desktop
Classifier: License :: OSI Approved :: GNU General Public License (GPL)
Classifier: Operating System :: OS Independent
Classifier: Topic :: Multimedia :: Graphics :: Editors :: Vector-Based
Classifier: Topic :: Office/Business :: Scheduling
Classifier: Topic :: Scientific/Engineering :: Visualization
Requires-Dist: python-gantt (>=0.6.0)
